danceschool_dancervax/__init__.py
danceschool_dancervax/apps.py
danceschool_dancervax/dynamic_preferences_registry.py
danceschool_dancervax/extras_templates.py
danceschool_dancervax/handlers.py
danceschool_dancervax/session.py
danceschool_dancervax/__pycache__/__init__.cpython-38.pyc
danceschool_dancervax/__pycache__/apps.cpython-38.pyc
danceschool_dancervax/__pycache__/dynamic_preferences_registry.cpython-38.pyc
danceschool_dancervax/__pycache__/extras_templates.cpython-38.pyc
danceschool_dancervax/__pycache__/handlers.cpython-38.pyc
danceschool_dancervax/__pycache__/session.cpython-38.pyc
danceschool_dancervax/static/danceschool_dancervax/status_response.js
danceschool_dancervax/templates/danceschool_dancervax/status_response.html
danceschool_dancervax-0.1.5.dist-info/LICENSE
danceschool_dancervax-0.1.5.dist-info/METADATA
danceschool_dancervax-0.1.5.dist-info/WHEEL
danceschool_dancervax-0.1.5.dist-info/top_level.txt
danceschool_dancervax-0.1.5.dist-info/RECORD
