Metadata-Version: 2.1
Name: danceschool-dancervax
Version: 0.1.5
Summary: DancerVax API integration for The Django Dance School project
Home-page: https://github.com/django-danceschool/danceschool-dancervax
Author: Lee Tucker
Author-email: lee.c.tucker@gmail.com
License: BSD License
Platform: UNKNOWN
Classifier: Environment :: Web Environment
Classifier: Framework :: Django
Classifier: Intended Audience :: Developers
Classifier: License :: OSI Approved :: BSD License
Classifier: Operating System :: OS Independent
Classifier: Programming Language :: Python
Classifier: Topic :: Internet :: WWW/HTTP
Classifier: Topic :: Internet :: WWW/HTTP :: Dynamic Content
Requires-Dist: Django (>=3.1.13)
Requires-Dist: django-danceschool (>=0.9.3)
Requires-Dist: requests-oauthlib (>=1.3.0)
Requires-Dist: requests (>=2.22.0)
